pdf_word_counter/__init__.py
pdf_word_counter/__main__.py
pdf_word_counter/cli.py
pdf_word_counter/output.py
pdf_word_counter/pdf_utils.py
pdf_word_counter/search.py
pdf_word_counter/utils.py
pdf_word_counter/version.py
pdf_word_counter-0.3.3.dist-info/licenses/LICENSE
pdf_word_counter-0.3.3.dist-info/METADATA
pdf_word_counter-0.3.3.dist-info/WHEEL
pdf_word_counter-0.3.3.dist-info/entry_points.txt
pdf_word_counter-0.3.3.dist-info/top_level.txt
pdf_word_counter-0.3.3.dist-info/RECORD
