Metadata-Version: 2.4
Name: pdf-word-counter
Version: 0.3.3
Summary: Search PDF files for specific words and generate frequency statistics.
Author-email: Rubén García-Benito <rgb@iaa.es>
License: MIT
Project-URL: Homepage, https://github.com/rgbIAA/pdf-word-counter
Keywords: pdf,text extraction,word count,command line tool
Classifier: Programming Language :: Python :: 3
Classifier: License :: OSI Approved :: MIT License
Classifier: Operating System :: OS Independent
Requires-Python: >=3.8
License-File: LICENSE
Requires-Dist: PyPDF2
Requires-Dist: astropy
Requires-Dist: tqdm
Requires-Dist: pandas
Provides-Extra: miner
Requires-Dist: pdfminer.six; extra == "miner"
Provides-Extra: astropy
Requires-Dist: astropy; extra == "astropy"
Dynamic: license-file
